{"version":1,"functions":{"/about":{},"/blog/[slug]":{},"/locations/[slug]":{},"/locations":{},"/portfolio/[slug]":{},"/portfolio":{},"/services/[service]/[location]":{},"/services/basement-finishing":{},"/privacy-policy":{},"/services/bathroom-remodeling":{},"/services/countertop-installation":{},"/services/home-additions":{},"/services/custom-cabinetry":{},"/services":{},"/services/kitchen-remodeling":{},"/services/interior-remodeling":{},"/terms-of-service":{},"/services/tile-flooring":{},"/testimonials":{}}}